tradepy/__init__.py
tradepy/version.py
tradepy-0.0.0.dist-info/METADATA
tradepy-0.0.0.dist-info/WHEEL
tradepy-0.0.0.dist-info/top_level.txt
tradepy-0.0.0.dist-info/RECORD
