Metadata-Version: 2.1
Name: tradepy
Version: 0.0.0
Summary: tradepy
Home-page: http://pypi.org/project/tradepy
License: UNKNOWN
Platform: UNKNOWN
Classifier: Programming Language :: Python
Classifier: Intended Audience :: Science/Research
